[
    {
        "_id": {
            "$oid": "664113acbb44e2c248032223"
        },
        "name": "הייטק"
    },
    {
        "_id": {
            "$oid": "664113acbb44e2c248032222"
        },
        "name": "בישול"
    },
    {
        "_id": {
            "$oid": "664113acbb44e2c248032225"
        },
        "name": "הוראה"
    },
    {
        "_id": {
            "$oid": "664113acbb44e2c248032226"
        },
        "name": "משפטים"
    },
    {
        "_id": {
            "$oid": "664113acbb44e2c248032227"
        },
        "name": "כלכלה"
    },
    {
        "_id": {
            "$oid": "664113acbb44e2c248032228"
        },
        "name": "ניהול"
    },
    {
        "_id": {
            "$oid": "664113acbb44e2c248032229"
        },
        "name": "תקשורת"
    },
    {
        "_id": {
            "$oid": "664113acbb44e2c248032224"
        },
        "name": "חשמל"
    }
]
